odoo/addons/purchase_supplier_rank/README.rst
odoo/addons/purchase_supplier_rank/__init__.py
odoo/addons/purchase_supplier_rank/__manifest__.py
odoo/addons/purchase_supplier_rank/i18n/purchase_supplier_rank.pot
odoo/addons/purchase_supplier_rank/models/__init__.py
odoo/addons/purchase_supplier_rank/models/purchase_order.py
odoo/addons/purchase_supplier_rank/readme/CONTRIBUTORS.rst
odoo/addons/purchase_supplier_rank/readme/DESCRIPTION.rst
odoo/addons/purchase_supplier_rank/static/description/icon.png
odoo/addons/purchase_supplier_rank/static/description/index.html
odoo13_addon_purchase_supplier_rank-13.0.1.0.1.dev3.dist-info/METADATA
odoo13_addon_purchase_supplier_rank-13.0.1.0.1.dev3.dist-info/WHEEL
odoo13_addon_purchase_supplier_rank-13.0.1.0.1.dev3.dist-info/top_level.txt
odoo13_addon_purchase_supplier_rank-13.0.1.0.1.dev3.dist-info/RECORD
